balancer_maths/__init__.py
balancer_maths/common/__init__.py
balancer_maths/common/base_pool_math.py
balancer_maths/common/base_pool_state.py
balancer_maths/common/bigint.py
balancer_maths/common/constants.py
balancer_maths/common/log_exp_math.py
balancer_maths/common/maths.py
balancer_maths/common/oz_math.py
balancer_maths/common/pool_base.py
balancer_maths/common/swap_params.py
balancer_maths/common/types.py
balancer_maths/common/utils.py
balancer_maths/hooks/__init__.py
balancer_maths/hooks/default_hook.py
balancer_maths/hooks/types.py
balancer_maths/hooks/exit_fee/exit_fee_hook.py
balancer_maths/hooks/exit_fee/types.py
balancer_maths/hooks/stable_surge/stable_surge_hook.py
balancer_maths/hooks/stable_surge/types.py
balancer_maths/pools/__init__.py
balancer_maths/pools/buffer/__init__.py
balancer_maths/pools/buffer/buffer_data.py
balancer_maths/pools/buffer/buffer_math.py
balancer_maths/pools/buffer/enums.py
balancer_maths/pools/buffer/erc4626_buffer_wrap_or_unwrap.py
balancer_maths/pools/gyro/__init__.py
balancer_maths/pools/gyro/gyro_2clp.py
balancer_maths/pools/gyro/gyro_2clp_data.py
balancer_maths/pools/gyro/gyro_2clp_math.py
balancer_maths/pools/gyro/gyro_eclp.py
balancer_maths/pools/gyro/gyro_eclp_data.py
balancer_maths/pools/gyro/gyro_eclp_math.py
balancer_maths/pools/gyro/gyro_pool_math.py
balancer_maths/pools/gyro/signed_fixed_point.py
balancer_maths/pools/liquidity_bootstrapping/__init__.py
balancer_maths/pools/liquidity_bootstrapping/liquidity_bootstrapping.py
balancer_maths/pools/liquidity_bootstrapping/liquidity_bootstrapping_data.py
balancer_maths/pools/liquidity_bootstrapping/liquidity_bootstrapping_math.py
balancer_maths/pools/quantamm/__init__.py
balancer_maths/pools/quantamm/quantamm.py
balancer_maths/pools/quantamm/quantamm_data.py
balancer_maths/pools/quantamm/quantamm_math.py
balancer_maths/pools/reclamm/__init__.py
balancer_maths/pools/reclamm/reclamm.py
balancer_maths/pools/reclamm/reclamm_data.py
balancer_maths-0.1.1.dist-info/METADATA
balancer_maths-0.1.1.dist-info/WHEEL
balancer_maths-0.1.1.dist-info/licenses/LICENSE
balancer_maths-0.1.1.dist-info/RECORD
