Metadata-Version: 2.4
Name: balancer-maths
Version: 0.1.1
Summary: Python implementation of mathematics for Balancer v3
Project-URL: Homepage, https://github.com/balancer/balancer-maths
Project-URL: Repository, https://github.com/balancer/balancer-maths
Project-URL: Documentation, https://github.com/balancer/balancer-maths/tree/main/python#readme
Project-URL: Bug Tracker, https://github.com/balancer/balancer-maths/issues
License: MIT
License-File: LICENSE
Keywords: amm,balancer,defi,liquidity,mathematics,pools
Requires-Python: >=3.10
Provides-Extra: dev
Requires-Dist: black>=22.0.0; extra == 'dev'
Requires-Dist: pytest>=7.0.0; extra == 'dev'
